[{"line":2,"elements":[{"line":4,"name":"","description":"","type":"background","keyword":"Background","steps":[{"result":{"duration":97864000,"status":"passed"},"line":5,"name":"User is on retail website","match":{"location":"tek.capstone.bdd.framework.steps.SignInSteps.userIsOnRetailWebsite()"},"keyword":"Given "}]},{"start_timestamp":"2023-03-10T17:48:06.872Z","before":[{"result":{"duration":5404934400,"status":"passed"},"match":{"location":"tek.capstone.bdd.framework.base.BaseUITest.setupTest()"}}],"line":8,"name":"Verify Shop by Department sidebar","description":"","id":"retail-home-page;verify-shop-by-department-sidebar","after":[{"result":{"duration":707154600,"status":"passed"},"match":{"location":"tek.capstone.bdd.framework.base.BaseUITest.closeTest(io.cucumber.java.Scenario)"}}],"type":"scenario","keyword":"Scenario","steps":[{"result":{"duration":306063000,"status":"passed"},"line":9,"name":"User click on All section","match":{"location":"tek.capstone.bdd.framework.steps.HomeSteps.userClickOnAllSection()"},"keyword":"When "},{"result":{"duration":144849800,"status":"passed"},"line":10,"name":"below options are present in Shop by Department sidebar","match":{"location":"tek.capstone.bdd.framework.steps.HomeSteps.belowOptionsShouldBePresent(io.cucumber.datatable.DataTable)"},"rows":[{"cells":["Electronics","Computers","Smart Home","Sports","Automative"]}],"keyword":"Then "}],"tags":[{"name":"@jenkins"},{"name":"@home1"}]},{"line":4,"name":"","description":"","type":"background","keyword":"Background","steps":[{"result":{"duration":62514900,"status":"passed"},"line":5,"name":"User is on retail website","match":{"location":"tek.capstone.bdd.framework.steps.SignInSteps.userIsOnRetailWebsite()"},"keyword":"Given "}]},{"start_timestamp":"2023-03-10T17:48:13.575Z","before":[{"result":{"duration":3105324000,"status":"passed"},"match":{"location":"tek.capstone.bdd.framework.base.BaseUITest.setupTest()"}}],"line":22,"name":"Verify department sidebar options","description":"","id":"retail-home-page;verify-department-sidebar-options;;2","after":[{"result":{"duration":528563500,"status":"passed"},"match":{"location":"tek.capstone.bdd.framework.base.BaseUITest.closeTest(io.cucumber.java.Scenario)"}}],"type":"scenario","keyword":"Scenario Outline","steps":[{"result":{"duration":306481900,"status":"passed"},"line":15,"name":"User click on All section","match":{"location":"tek.capstone.bdd.framework.steps.HomeSteps.userClickOnAllSection()"},"keyword":"When "},{"result":{"duration":241297900,"status":"passed"},"line":16,"name":"User on 'Electronics'","match":{"arguments":[{"val":"'Electronics'","offset":8}],"location":"tek.capstone.bdd.framework.steps.HomeSteps.userOnDepartment(java.lang.String)"},"keyword":"And "},{"result":{"duration":66381600,"status":"passed"},"line":17,"name":"below options are present in department","match":{"location":"tek.capstone.bdd.framework.steps.HomeSteps.belowOptionsArePresentInDepartment(io.cucumber.datatable.DataTable)"},"rows":[{"cells":["TV & Video","Video Games"]}],"keyword":"Then "}],"tags":[{"name":"@jenkins"},{"name":"@home2"}]},{"line":4,"name":"","description":"","type":"background","keyword":"Background","steps":[{"result":{"duration":62908800,"status":"passed"},"line":5,"name":"User is on retail website","match":{"location":"tek.capstone.bdd.framework.steps.SignInSteps.userIsOnRetailWebsite()"},"keyword":"Given "}]},{"start_timestamp":"2023-03-10T17:48:17.900Z","before":[{"result":{"duration":3036514800,"status":"passed"},"match":{"location":"tek.capstone.bdd.framework.base.BaseUITest.setupTest()"}}],"line":23,"name":"Verify department sidebar options","description":"","id":"retail-home-page;verify-department-sidebar-options;;3","after":[{"result":{"duration":568422000,"status":"passed"},"match":{"location":"tek.capstone.bdd.framework.base.BaseUITest.closeTest(io.cucumber.java.Scenario)"}}],"type":"scenario","keyword":"Scenario Outline","steps":[{"result":{"duration":320565000,"status":"passed"},"line":15,"name":"User click on All section","match":{"location":"tek.capstone.bdd.framework.steps.HomeSteps.userClickOnAllSection()"},"keyword":"When "},{"result":{"duration":264678600,"status":"passed"},"line":16,"name":"User on 'Computers'","match":{"arguments":[{"val":"'Computers'","offset":8}],"location":"tek.capstone.bdd.framework.steps.HomeSteps.userOnDepartment(java.lang.String)"},"keyword":"And "},{"result":{"duration":76260500,"status":"passed"},"line":17,"name":"below options are present in department","match":{"location":"tek.capstone.bdd.framework.steps.HomeSteps.belowOptionsArePresentInDepartment(io.cucumber.datatable.DataTable)"},"rows":[{"cells":["Accessories","Networking"]}],"keyword":"Then "}],"tags":[{"name":"@jenkins"},{"name":"@home2"}]},{"line":4,"name":"","description":"","type":"background","keyword":"Background","steps":[{"result":{"duration":43999500,"status":"passed"},"line":5,"name":"User is on retail website","match":{"location":"tek.capstone.bdd.framework.steps.SignInSteps.userIsOnRetailWebsite()"},"keyword":"Given "}]},{"start_timestamp":"2023-03-10T17:48:22.241Z","before":[{"result":{"duration":3184952800,"status":"passed"},"match":{"location":"tek.capstone.bdd.framework.base.BaseUITest.setupTest()"}}],"line":24,"name":"Verify department sidebar options","description":"","id":"retail-home-page;verify-department-sidebar-options;;4","after":[{"result":{"duration":645910900,"status":"passed"},"match":{"location":"tek.capstone.bdd.framework.base.BaseUITest.closeTest(io.cucumber.java.Scenario)"}}],"type":"scenario","keyword":"Scenario Outline","steps":[{"result":{"duration":307195800,"status":"passed"},"line":15,"name":"User click on All section","match":{"location":"tek.capstone.bdd.framework.steps.HomeSteps.userClickOnAllSection()"},"keyword":"When "},{"result":{"duration":258875200,"status":"passed"},"line":16,"name":"User on 'Smart Home'","match":{"arguments":[{"val":"'Smart Home'","offset":8}],"location":"tek.capstone.bdd.framework.steps.HomeSteps.userOnDepartment(java.lang.String)"},"keyword":"And "},{"result":{"duration":70602600,"status":"passed"},"line":17,"name":"below options are present in department","match":{"location":"tek.capstone.bdd.framework.steps.HomeSteps.belowOptionsArePresentInDepartment(io.cucumber.datatable.DataTable)"},"rows":[{"cells":["Smart Home Lightning","Plugs and Outlets"]}],"keyword":"Then "}],"tags":[{"name":"@jenkins"},{"name":"@home2"}]},{"line":4,"name":"","description":"","type":"background","keyword":"Background","steps":[{"result":{"duration":54267200,"status":"passed"},"line":5,"name":"User is on retail website","match":{"location":"tek.capstone.bdd.framework.steps.SignInSteps.userIsOnRetailWebsite()"},"keyword":"Given "}]},{"start_timestamp":"2023-03-10T17:48:26.765Z","before":[{"result":{"duration":3188316400,"status":"passed"},"match":{"location":"tek.capstone.bdd.framework.base.BaseUITest.setupTest()"}}],"line":25,"name":"Verify department sidebar options","description":"","id":"retail-home-page;verify-department-sidebar-options;;5","after":[{"result":{"duration":522444100,"status":"passed"},"match":{"location":"tek.capstone.bdd.framework.base.BaseUITest.closeTest(io.cucumber.java.Scenario)"}}],"type":"scenario","keyword":"Scenario Outline","steps":[{"result":{"duration":310789500,"status":"passed"},"line":15,"name":"User click on All section","match":{"location":"tek.capstone.bdd.framework.steps.HomeSteps.userClickOnAllSection()"},"keyword":"When "},{"result":{"duration":273910400,"status":"passed"},"line":16,"name":"User on 'Sports'","match":{"arguments":[{"val":"'Sports'","offset":8}],"location":"tek.capstone.bdd.framework.steps.HomeSteps.userOnDepartment(java.lang.String)"},"keyword":"And "},{"result":{"duration":59107300,"status":"passed"},"line":17,"name":"below options are present in department","match":{"location":"tek.capstone.bdd.framework.steps.HomeSteps.belowOptionsArePresentInDepartment(io.cucumber.datatable.DataTable)"},"rows":[{"cells":["Athletic Clothing","Exercise & Fitness"]}],"keyword":"Then "}],"tags":[{"name":"@jenkins"},{"name":"@home2"}]},{"line":4,"name":"","description":"","type":"background","keyword":"Background","steps":[{"result":{"duration":57337700,"status":"passed"},"line":5,"name":"User is on retail website","match":{"location":"tek.capstone.bdd.framework.steps.SignInSteps.userIsOnRetailWebsite()"},"keyword":"Given "}]},{"start_timestamp":"2023-03-10T17:48:31.182Z","before":[{"result":{"duration":3046845100,"status":"passed"},"match":{"location":"tek.capstone.bdd.framework.base.BaseUITest.setupTest()"}}],"line":26,"name":"Verify department sidebar options","description":"","id":"retail-home-page;verify-department-sidebar-options;;6","after":[{"result":{"duration":526913500,"status":"passed"},"match":{"location":"tek.capstone.bdd.framework.base.BaseUITest.closeTest(io.cucumber.java.Scenario)"}}],"type":"scenario","keyword":"Scenario Outline","steps":[{"result":{"duration":277422000,"status":"passed"},"line":15,"name":"User click on All section","match":{"location":"tek.capstone.bdd.framework.steps.HomeSteps.userClickOnAllSection()"},"keyword":"When "},{"result":{"duration":59686500,"status":"passed"},"line":16,"name":"User on 'Automotive'","match":{"arguments":[{"val":"'Automotive'","offset":8}],"location":"tek.capstone.bdd.framework.steps.HomeSteps.userOnDepartment(java.lang.String)"},"keyword":"And "},{"result":{"duration":63804000,"status":"passed"},"line":17,"name":"below options are present in department","match":{"location":"tek.capstone.bdd.framework.steps.HomeSteps.belowOptionsArePresentInDepartment(io.cucumber.datatable.DataTable)"},"rows":[{"cells":["Automative Parts & Accessories","MotorCycle & Powersports"]}],"keyword":"Then "}],"tags":[{"name":"@jenkins"},{"name":"@home2"}]},{"line":4,"name":"","description":"","type":"background","keyword":"Background","steps":[{"result":{"duration":57269600,"status":"passed"},"line":5,"name":"User is on retail website","match":{"location":"tek.capstone.bdd.framework.steps.SignInSteps.userIsOnRetailWebsite()"},"keyword":"Given "}]},{"start_timestamp":"2023-03-10T17:48:35.234Z","before":[{"result":{"duration":3021330800,"status":"passed"},"match":{"location":"tek.capstone.bdd.framework.base.BaseUITest.setupTest()"}}],"line":29,"name":"Verify User can add an item to cart","description":"","id":"retail-home-page;verify-user-can-add-an-item-to-cart","after":[{"result":{"duration":660422700,"status":"passed"},"match":{"location":"tek.capstone.bdd.framework.base.BaseUITest.closeTest(io.cucumber.java.Scenario)"}}],"type":"scenario","keyword":"Scenario","steps":[{"result":{"duration":17002300,"status":"passed"},"line":30,"name":"User is on retail website","match":{"location":"tek.capstone.bdd.framework.steps.SignInSteps.userIsOnRetailWebsite()"},"keyword":"Given "},{"result":{"duration":287673000,"status":"passed"},"line":31,"name":"User click on Sign in option","match":{"location":"tek.capstone.bdd.framework.steps.SignInSteps.userClickOnSignIn()"},"keyword":"When "},{"result":{"duration":134742600,"status":"passed"},"line":32,"name":"User enter email 'email' and password 'password'","match":{"arguments":[{"val":"'email'","offset":17},{"val":"'password'","offset":38}],"location":"tek.capstone.bdd.framework.steps.SignInSteps.userEnterEmailAndPassword(java.lang.String,java.lang.String)"},"keyword":"And "},{"result":{"duration":254706100,"status":"passed"},"line":33,"name":"User click on login button","match":{"location":"tek.capstone.bdd.framework.steps.SignInSteps.userClickOnLoginBtn()"},"keyword":"And "},{"result":{"duration":74839300,"status":"passed"},"line":34,"name":"User should be logged in into Account","match":{"location":"tek.capstone.bdd.framework.steps.SignInSteps.userShouldBeLoggedIn()"},"keyword":"And "},{"result":{"duration":268890200,"status":"passed"},"line":35,"name":"User change the category to 'Smart Home'","match":{"arguments":[{"val":"'Smart Home'","offset":28}],"location":"tek.capstone.bdd.framework.steps.HomeSteps.userChangeCategory(java.lang.String)"},"keyword":"And "},{"result":{"duration":73123100,"status":"passed"},"line":36,"name":"User search for an item 'kasa outdoor smart plug'","match":{"arguments":[{"val":"'kasa outdoor smart plug'","offset":24}],"location":"tek.capstone.bdd.framework.steps.HomeSteps.userSearchForAnItem(java.lang.String)"},"keyword":"And "},{"result":{"duration":267228900,"status":"passed"},"line":37,"name":"User click on Search icon","match":{"location":"tek.capstone.bdd.framework.steps.HomeSteps.userClickOnSearchIcon()"},"keyword":"And "},{"result":{"duration":256458100,"status":"passed"},"line":38,"name":"User click on item","match":{"location":"tek.capstone.bdd.framework.steps.HomeSteps.userClickOnItem()"},"keyword":"And "},{"result":{"duration":237033200,"status":"passed"},"line":39,"name":"User select quantity '2'","match":{"arguments":[{"val":"'2'","offset":21}],"location":"tek.capstone.bdd.framework.steps.HomeSteps.userSelectQuantity(java.lang.String)"},"keyword":"And "},{"result":{"duration":238282100,"status":"passed"},"line":40,"name":"User click add to Cart button","match":{"location":"tek.capstone.bdd.framework.steps.HomeSteps.userClickOnAddToCartBtn()"},"keyword":"And "},{"result":{"duration":566217700,"status":"passed"},"line":41,"name":"the cart icon quantity should change to '2'","match":{"arguments":[{"val":"'2'","offset":40}],"location":"tek.capstone.bdd.framework.steps.HomeSteps.theCartIconShouldChange(java.lang.String)"},"keyword":"Then "}],"tags":[{"name":"@jenkins"},{"name":"@home3"}]},{"line":4,"name":"","description":"","type":"background","keyword":"Background","steps":[{"result":{"duration":62528100,"status":"passed"},"line":5,"name":"User is on retail website","match":{"location":"tek.capstone.bdd.framework.steps.SignInSteps.userIsOnRetailWebsite()"},"keyword":"Given "}]},{"start_timestamp":"2023-03-10T17:48:41.670Z","before":[{"result":{"duration":3180294100,"status":"passed"},"match":{"location":"tek.capstone.bdd.framework.base.BaseUITest.setupTest()"}}],"line":44,"name":"Verify User can place an order without Shipping address and payment Method on file","description":"","id":"retail-home-page;verify-user-can-place-an-order-without-shipping-address-and-payment-method-on-file","after":[{"result":{"duration":531397500,"status":"passed"},"match":{"location":"tek.capstone.bdd.framework.base.BaseUITest.closeTest(io.cucumber.java.Scenario)"}}],"type":"scenario","keyword":"Scenario","steps":[{"result":{"duration":293197900,"status":"passed"},"line":45,"name":"User click on Sign in option","match":{"location":"tek.capstone.bdd.framework.steps.SignInSteps.userClickOnSignIn()"},"keyword":"When "},{"result":{"duration":122675300,"status":"passed"},"line":46,"name":"User enter email 'email' and password 'password'","match":{"arguments":[{"val":"'email'","offset":17},{"val":"'password'","offset":38}],"location":"tek.capstone.bdd.framework.steps.SignInSteps.userEnterEmailAndPassword(java.lang.String,java.lang.String)"},"keyword":"And "},{"result":{"duration":262505300,"status":"passed"},"line":47,"name":"User click on login button","match":{"location":"tek.capstone.bdd.framework.steps.SignInSteps.userClickOnLoginBtn()"},"keyword":"And "},{"result":{"duration":101012300,"status":"passed"},"line":48,"name":"User should be logged in into Account","match":{"location":"tek.capstone.bdd.framework.steps.SignInSteps.userShouldBeLoggedIn()"},"keyword":"And "},{"result":{"duration":286660500,"status":"passed"},"line":49,"name":"User change the category to 'Smart Home'","match":{"arguments":[{"val":"'Smart Home'","offset":28}],"location":"tek.capstone.bdd.framework.steps.HomeSteps.userChangeCategory(java.lang.String)"},"keyword":"And "},{"result":{"duration":74173400,"status":"passed"},"line":50,"name":"User search for an item 'kasa outdoor smart plug'","match":{"arguments":[{"val":"'kasa outdoor smart plug'","offset":24}],"location":"tek.capstone.bdd.framework.steps.HomeSteps.userSearchForAnItem(java.lang.String)"},"keyword":"And "},{"result":{"duration":277972200,"status":"passed"},"line":51,"name":"User click on Search icon","match":{"location":"tek.capstone.bdd.framework.steps.HomeSteps.userClickOnSearchIcon()"},"keyword":"And "},{"result":{"duration":248016400,"status":"passed"},"line":52,"name":"User click on item","match":{"location":"tek.capstone.bdd.framework.steps.HomeSteps.userClickOnItem()"},"keyword":"And "},{"result":{"duration":234527400,"status":"passed"},"line":53,"name":"User select quantity '2'","match":{"arguments":[{"val":"'2'","offset":21}],"location":"tek.capstone.bdd.framework.steps.HomeSteps.userSelectQuantity(java.lang.String)"},"keyword":"And "},{"result":{"duration":238005500,"status":"passed"},"line":54,"name":"User click add to Cart button","match":{"location":"tek.capstone.bdd.framework.steps.HomeSteps.userClickOnAddToCartBtn()"},"keyword":"And "},{"result":{"duration":1078240000,"status":"passed"},"line":55,"name":"the cart icon quantity should change to '2'","match":{"arguments":[{"val":"'2'","offset":40}],"location":"tek.capstone.bdd.framework.steps.HomeSteps.theCartIconShouldChange(java.lang.String)"},"keyword":"Then "},{"result":{"duration":234136600,"status":"passed"},"line":56,"name":"User click on Cart option","match":{"location":"tek.capstone.bdd.framework.steps.HomeSteps.userClickOnCartOption()"},"keyword":"And "},{"result":{"duration":245754500,"status":"passed"},"line":57,"name":"User click on Proceed to Checkout button","match":{"location":"tek.capstone.bdd.framework.steps.HomeSteps.userClickOnProceedToCheckoutBtn()"},"keyword":"And "},{"result":{"duration":244998900,"status":"passed"},"line":58,"name":"User click Add a new address link for shipping address","match":{"location":"tek.capstone.bdd.framework.steps.HomeSteps.userClickOnAddANewAddressLink()"},"keyword":"And "},{"result":{"duration":840936000,"status":"passed"},"line":59,"name":"User fill new address form with below information","match":{"location":"tek.capstone.bdd.framework.steps.RetailAccountSteps.userFillAddressInfo(io.cucumber.datatable.DataTable)"},"rows":[{"cells":["country","fullName","phoneNumber","streetAddress","apt","city","state","zipCode"]},{"cells":["United States","fullName","phoneNumber","streetAddress","123","city","California","zipCode"]}],"keyword":"And "},{"result":{"duration":269819800,"status":"passed"},"line":62,"name":"User click Add Your Address button","match":{"location":"tek.capstone.bdd.framework.steps.RetailAccountSteps.userClickAddYourAddressBtn()"},"keyword":"And "},{"result":{"duration":235387500,"status":"passed"},"line":63,"name":"User click Add a credit card or Debit Card for Payment method","match":{"location":"tek.capstone.bdd.framework.steps.HomeSteps.userClickAddACreditOrDebitCardLink()"},"keyword":"And "},{"result":{"duration":567949300,"status":"passed"},"line":64,"name":"User fill Debit or credit card information","match":{"location":"tek.capstone.bdd.framework.steps.RetailAccountSteps.userFillDebitOrCreditCardInfo(io.cucumber.datatable.DataTable)"},"rows":[{"cells":["cardNumber","nameOnCard","expirationMonth","expirationYear","securityCode"]},{"cells":["cardNumber","fullName","4","2024","789"]}],"keyword":"And "},{"result":{"duration":232121400,"status":"passed"},"line":67,"name":"User click on Add your card button","match":{"location":"tek.capstone.bdd.framework.steps.RetailAccountSteps.userClickOnAddYourCardBtn()"},"keyword":"And "},{"result":{"duration":242219500,"status":"passed"},"line":68,"name":"User click on Place Your Order","match":{"location":"tek.capstone.bdd.framework.steps.HomeSteps.userClickOnPlaceYourOrder()"},"keyword":"And "},{"result":{"duration":39603600,"status":"passed"},"line":69,"name":"a message should be displayed ‘Order Placed, Thanks’","match":{"location":"tek.capstone.bdd.framework.steps.HomeSteps.orderPlacedMessageShouldBeDisplayed()"},"keyword":"Then "}],"tags":[{"name":"@jenkins"},{"name":"@home4"}]},{"line":4,"name":"","description":"","type":"background","keyword":"Background","steps":[{"result":{"duration":39419200,"status":"passed"},"line":5,"name":"User is on retail website","match":{"location":"tek.capstone.bdd.framework.steps.SignInSteps.userIsOnRetailWebsite()"},"keyword":"Given "}]},{"start_timestamp":"2023-03-10T17:48:51.841Z","before":[{"result":{"duration":2983967200,"status":"passed"},"match":{"location":"tek.capstone.bdd.framework.base.BaseUITest.setupTest()"}}],"line":72,"name":"Verify User can place an order with Shipping address and payment Method on file","description":"","id":"retail-home-page;verify-user-can-place-an-order-with-shipping-address-and-payment-method-on-file","after":[{"result":{"duration":655864400,"status":"passed"},"match":{"location":"tek.capstone.bdd.framework.base.BaseUITest.closeTest(io.cucumber.java.Scenario)"}}],"type":"scenario","keyword":"Scenario","steps":[{"result":{"duration":313788000,"status":"passed"},"line":73,"name":"User click on Sign in option","match":{"location":"tek.capstone.bdd.framework.steps.SignInSteps.userClickOnSignIn()"},"keyword":"When "},{"result":{"duration":99615200,"status":"passed"},"line":74,"name":"User enter email 'email' and password 'password'","match":{"arguments":[{"val":"'email'","offset":17},{"val":"'password'","offset":38}],"location":"tek.capstone.bdd.framework.steps.SignInSteps.userEnterEmailAndPassword(java.lang.String,java.lang.String)"},"keyword":"And "},{"result":{"duration":241778100,"status":"passed"},"line":75,"name":"User click on login button","match":{"location":"tek.capstone.bdd.framework.steps.SignInSteps.userClickOnLoginBtn()"},"keyword":"And "},{"result":{"duration":169749200,"status":"passed"},"line":76,"name":"User should be logged in into Account","match":{"location":"tek.capstone.bdd.framework.steps.SignInSteps.userShouldBeLoggedIn()"},"keyword":"And "},{"result":{"duration":277888100,"status":"passed"},"line":77,"name":"User change the category to 'Electronics'","match":{"arguments":[{"val":"'Electronics'","offset":28}],"location":"tek.capstone.bdd.framework.steps.HomeSteps.userChangeCategory(java.lang.String)"},"keyword":"And "},{"result":{"duration":62500400,"status":"passed"},"line":78,"name":"User search for an item 'Apex Legends'","match":{"arguments":[{"val":"'Apex Legends'","offset":24}],"location":"tek.capstone.bdd.framework.steps.HomeSteps.userSearchForAnItem(java.lang.String)"},"keyword":"And "},{"result":{"duration":263944300,"status":"passed"},"line":79,"name":"User click on Search icon","match":{"location":"tek.capstone.bdd.framework.steps.HomeSteps.userClickOnSearchIcon()"},"keyword":"And "},{"result":{"duration":264912400,"status":"passed"},"line":80,"name":"User click on item","match":{"location":"tek.capstone.bdd.framework.steps.HomeSteps.userClickOnItem()"},"keyword":"And "},{"result":{"duration":233266500,"status":"passed"},"line":81,"name":"User select quantity '5'","match":{"arguments":[{"val":"'5'","offset":21}],"location":"tek.capstone.bdd.framework.steps.HomeSteps.userSelectQuantity(java.lang.String)"},"keyword":"And "},{"result":{"duration":233682600,"status":"passed"},"line":82,"name":"User click add to Cart button","match":{"location":"tek.capstone.bdd.framework.steps.HomeSteps.userClickOnAddToCartBtn()"},"keyword":"And "},{"result":{"duration":259573800,"status":"passed"},"line":83,"name":"the cart icon quantity should change to '5'","match":{"arguments":[{"val":"'5'","offset":40}],"location":"tek.capstone.bdd.framework.steps.HomeSteps.theCartIconShouldChange(java.lang.String)"},"keyword":"Then "},{"result":{"duration":229350900,"status":"passed"},"line":84,"name":"User click on Cart option","match":{"location":"tek.capstone.bdd.framework.steps.HomeSteps.userClickOnCartOption()"},"keyword":"And "},{"result":{"duration":256324300,"status":"passed"},"line":85,"name":"User click on Proceed to Checkout button","match":{"location":"tek.capstone.bdd.framework.steps.HomeSteps.userClickOnProceedToCheckoutBtn()"},"keyword":"And "},{"result":{"duration":236138100,"status":"passed"},"line":86,"name":"User click on Place Your Order","match":{"location":"tek.capstone.bdd.framework.steps.HomeSteps.userClickOnPlaceYourOrder()"},"keyword":"And "},{"result":{"duration":37381300,"status":"passed"},"line":87,"name":"a message should be displayed ‘Order Placed, Thanks’","match":{"location":"tek.capstone.bdd.framework.steps.HomeSteps.orderPlacedMessageShouldBeDisplayed()"},"keyword":"Then "}],"tags":[{"name":"@jenkins"},{"name":"@home5"}]}],"name":"Retail Home Page","description":"","id":"retail-home-page","keyword":"Feature","uri":"classpath:features/Home.feature","tags":[{"name":"@jenkins","type":"Tag","location":{"line":1,"column":1}}]},{"line":2,"elements":[{"line":4,"name":"","description":"","type":"background","keyword":"Background","steps":[{"result":{"duration":44327900,"status":"passed"},"line":5,"name":"User is on retail website","match":{"location":"tek.capstone.bdd.framework.steps.SignInSteps.userIsOnRetailWebsite()"},"keyword":"Given "},{"result":{"duration":297465800,"status":"passed"},"line":6,"name":"User click on Sign in option","match":{"location":"tek.capstone.bdd.framework.steps.SignInSteps.userClickOnSignIn()"},"keyword":"When "},{"result":{"duration":117980000,"status":"passed"},"line":7,"name":"User enter email 'email' and password 'password'","match":{"arguments":[{"val":"'email'","offset":17},{"val":"'password'","offset":38}],"location":"tek.capstone.bdd.framework.steps.SignInSteps.userEnterEmailAndPassword(java.lang.String,java.lang.String)"},"keyword":"And "},{"result":{"duration":246417500,"status":"passed"},"line":8,"name":"User click on login button","match":{"location":"tek.capstone.bdd.framework.steps.SignInSteps.userClickOnLoginBtn()"},"keyword":"And "},{"result":{"duration":50667300,"status":"passed"},"line":9,"name":"User should be logged in into Account","match":{"location":"tek.capstone.bdd.framework.steps.SignInSteps.userShouldBeLoggedIn()"},"keyword":"And "},{"result":{"duration":278261100,"status":"passed"},"line":10,"name":"User click on Account option","match":{"location":"tek.capstone.bdd.framework.steps.RetailAccountSteps.userClickOnAccountOption()"},"keyword":"When "}]},{"start_timestamp":"2023-03-10T17:48:58.720Z","before":[{"result":{"duration":3111835500,"status":"passed"},"match":{"location":"tek.capstone.bdd.framework.base.BaseUITest.setupTest()"}}],"line":13,"name":"Verify User can update Profile Information","description":"","id":"retail-account-page;verify-user-can-update-profile-information","after":[{"result":{"duration":670717900,"status":"passed"},"match":{"location":"tek.capstone.bdd.framework.base.BaseUITest.closeTest(io.cucumber.java.Scenario)"}}],"type":"scenario","keyword":"Scenario","steps":[{"result":{"duration":175418000,"status":"passed"},"line":14,"name":"User update Name 'firstName' and Phone 'phoneNumber'","match":{"arguments":[{"val":"'firstName'","offset":17},{"val":"'phoneNumber'","offset":39}],"location":"tek.capstone.bdd.framework.steps.RetailAccountSteps.userUpdateNameAndPhone(java.lang.String,java.lang.String)"},"keyword":"And "},{"result":{"duration":237050900,"status":"passed"},"line":15,"name":"User click on Update button","match":{"location":"tek.capstone.bdd.framework.steps.RetailAccountSteps.userClickOnUpdateBtn()"},"keyword":"And "},{"result":{"duration":551464800,"status":"passed"},"line":16,"name":"user profile information should be updated","match":{"location":"tek.capstone.bdd.framework.steps.RetailAccountSteps.userProfileShouldBeUpdated()"},"keyword":"Then "}],"tags":[{"name":"@jenkins"},{"name":"@account1"}]},{"line":4,"name":"","description":"","type":"background","keyword":"Background","steps":[{"result":{"duration":40488400,"status":"passed"},"line":5,"name":"User is on retail website","match":{"location":"tek.capstone.bdd.framework.steps.SignInSteps.userIsOnRetailWebsite()"},"keyword":"Given "},{"result":{"duration":294713800,"status":"passed"},"line":6,"name":"User click on Sign in option","match":{"location":"tek.capstone.bdd.framework.steps.SignInSteps.userClickOnSignIn()"},"keyword":"When "},{"result":{"duration":184545100,"status":"passed"},"line":7,"name":"User enter email 'email' and password 'password'","match":{"arguments":[{"val":"'email'","offset":17},{"val":"'password'","offset":38}],"location":"tek.capstone.bdd.framework.steps.SignInSteps.userEnterEmailAndPassword(java.lang.String,java.lang.String)"},"keyword":"And "},{"result":{"duration":267701200,"status":"passed"},"line":8,"name":"User click on login button","match":{"location":"tek.capstone.bdd.framework.steps.SignInSteps.userClickOnLoginBtn()"},"keyword":"And "},{"result":{"duration":79850400,"status":"passed"},"line":9,"name":"User should be logged in into Account","match":{"location":"tek.capstone.bdd.framework.steps.SignInSteps.userShouldBeLoggedIn()"},"keyword":"And "},{"result":{"duration":274983500,"status":"passed"},"line":10,"name":"User click on Account option","match":{"location":"tek.capstone.bdd.framework.steps.RetailAccountSteps.userClickOnAccountOption()"},"keyword":"When "}]},{"start_timestamp":"2023-03-10T17:49:04.510Z","before":[{"result":{"duration":2995038700,"status":"passed"},"match":{"location":"tek.capstone.bdd.framework.base.BaseUITest.setupTest()"}}],"line":19,"name":"Verify User can add a payment method","description":"","id":"retail-account-page;verify-user-can-add-a-payment-method","after":[{"result":{"duration":624552100,"status":"passed"},"match":{"location":"tek.capstone.bdd.framework.base.BaseUITest.closeTest(io.cucumber.java.Scenario)"}}],"type":"scenario","keyword":"Scenario","steps":[{"result":{"duration":233160400,"status":"passed"},"line":20,"name":"User click on Add a payment method link","match":{"location":"tek.capstone.bdd.framework.steps.RetailAccountSteps.userClickOnAddPaymentLink()"},"keyword":"And "},{"result":{"duration":598279200,"status":"passed"},"line":21,"name":"User fill Debit or credit card information","match":{"location":"tek.capstone.bdd.framework.steps.RetailAccountSteps.userFillDebitOrCreditCardInfo(io.cucumber.datatable.DataTable)"},"rows":[{"cells":["cardNumber","nameOnCard","expirationMonth","expirationYear","securityCode"]},{"cells":["cardNumber","fullName","5","2025","120"]}],"keyword":"And "},{"result":{"duration":263418400,"status":"passed"},"line":24,"name":"User click on Add your card button","match":{"location":"tek.capstone.bdd.framework.steps.RetailAccountSteps.userClickOnAddYourCardBtn()"},"keyword":"And "},{"result":{"duration":552968200,"status":"passed"},"line":25,"name":"a message should be displayed ‘Payment Method added successfully’","match":{"location":"tek.capstone.bdd.framework.steps.RetailAccountSteps.paymentAddedMessageShouldBeDisplayed()"},"keyword":"Then "}],"tags":[{"name":"@jenkins"},{"name":"@account3"}]},{"line":4,"name":"","description":"","type":"background","keyword":"Background","steps":[{"result":{"duration":40510000,"status":"passed"},"line":5,"name":"User is on retail website","match":{"location":"tek.capstone.bdd.framework.steps.SignInSteps.userIsOnRetailWebsite()"},"keyword":"Given "},{"result":{"duration":305282300,"status":"passed"},"line":6,"name":"User click on Sign in option","match":{"location":"tek.capstone.bdd.framework.steps.SignInSteps.userClickOnSignIn()"},"keyword":"When "},{"result":{"duration":103594200,"status":"passed"},"line":7,"name":"User enter email 'email' and password 'password'","match":{"arguments":[{"val":"'email'","offset":17},{"val":"'password'","offset":38}],"location":"tek.capstone.bdd.framework.steps.SignInSteps.userEnterEmailAndPassword(java.lang.String,java.lang.String)"},"keyword":"And "},{"result":{"duration":253624300,"status":"passed"},"line":8,"name":"User click on login button","match":{"location":"tek.capstone.bdd.framework.steps.SignInSteps.userClickOnLoginBtn()"},"keyword":"And "},{"result":{"duration":49221200,"status":"passed"},"line":9,"name":"User should be logged in into Account","match":{"location":"tek.capstone.bdd.framework.steps.SignInSteps.userShouldBeLoggedIn()"},"keyword":"And "},{"result":{"duration":271628100,"status":"passed"},"line":10,"name":"User click on Account option","match":{"location":"tek.capstone.bdd.framework.steps.RetailAccountSteps.userClickOnAccountOption()"},"keyword":"When "}]},{"start_timestamp":"2023-03-10T17:49:10.939Z","before":[{"result":{"duration":3002926300,"status":"passed"},"match":{"location":"tek.capstone.bdd.framework.base.BaseUITest.setupTest()"}}],"line":28,"name":"Verify User can edit Debit or Credit card","description":"","id":"retail-account-page;verify-user-can-edit-debit-or-credit-card","after":[{"result":{"duration":666915300,"status":"passed"},"match":{"location":"tek.capstone.bdd.framework.base.BaseUITest.closeTest(io.cucumber.java.Scenario)"}}],"type":"scenario","keyword":"Scenario","steps":[{"result":{"duration":1016775800,"status":"passed"},"line":29,"name":"User click on Edit option of card section","match":{"location":"tek.capstone.bdd.framework.steps.RetailAccountSteps.userClickOnEditOptionOfCard()"},"keyword":"And "},{"result":{"duration":642510700,"status":"passed"},"line":30,"name":"user edit information with below data","match":{"location":"tek.capstone.bdd.framework.steps.RetailAccountSteps.userEditInfo(io.cucumber.datatable.DataTable)"},"rows":[{"cells":["cardNumber","nameOnCard","expirationMonth","expirationYear","securityCode"]},{"cells":["cardNumber","fullName","6","2026","234"]}],"keyword":"And "},{"result":{"duration":247016300,"status":"passed"},"line":33,"name":"user click on Update Your Card button","match":{"location":"tek.capstone.bdd.framework.steps.RetailAccountSteps.userClickOnUpdateYourCardBtn()"},"keyword":"And "},{"result":{"duration":560904900,"status":"passed"},"line":34,"name":"a message should be displayed ‘Payment Method updated Successfully’","match":{"location":"tek.capstone.bdd.framework.steps.RetailAccountSteps.paymendUpdatedMessageShouldBeDisplayed()"},"keyword":"Then "}],"tags":[{"name":"@jenkins"},{"name":"@account4"}]},{"line":4,"name":"","description":"","type":"background","keyword":"Background","steps":[{"result":{"duration":40135800,"status":"passed"},"line":5,"name":"User is on retail website","match":{"location":"tek.capstone.bdd.framework.steps.SignInSteps.userIsOnRetailWebsite()"},"keyword":"Given "},{"result":{"duration":289563700,"status":"passed"},"line":6,"name":"User click on Sign in option","match":{"location":"tek.capstone.bdd.framework.steps.SignInSteps.userClickOnSignIn()"},"keyword":"When "},{"result":{"duration":131769300,"status":"passed"},"line":7,"name":"User enter email 'email' and password 'password'","match":{"arguments":[{"val":"'email'","offset":17},{"val":"'password'","offset":38}],"location":"tek.capstone.bdd.framework.steps.SignInSteps.userEnterEmailAndPassword(java.lang.String,java.lang.String)"},"keyword":"And "},{"result":{"duration":254258500,"status":"passed"},"line":8,"name":"User click on login button","match":{"location":"tek.capstone.bdd.framework.steps.SignInSteps.userClickOnLoginBtn()"},"keyword":"And "},{"result":{"duration":36138600,"status":"passed"},"line":9,"name":"User should be logged in into Account","match":{"location":"tek.capstone.bdd.framework.steps.SignInSteps.userShouldBeLoggedIn()"},"keyword":"And "},{"result":{"duration":261636000,"status":"passed"},"line":10,"name":"User click on Account option","match":{"location":"tek.capstone.bdd.framework.steps.RetailAccountSteps.userClickOnAccountOption()"},"keyword":"When "}]},{"start_timestamp":"2023-03-10T17:49:18.111Z","before":[{"result":{"duration":2895933400,"status":"passed"},"match":{"location":"tek.capstone.bdd.framework.base.BaseUITest.setupTest()"}}],"line":37,"name":"Verify User can remove Debit or Credit card","description":"","id":"retail-account-page;verify-user-can-remove-debit-or-credit-card","after":[{"result":{"duration":517548500,"status":"passed"},"match":{"location":"tek.capstone.bdd.framework.base.BaseUITest.closeTest(io.cucumber.java.Scenario)"}}],"type":"scenario","keyword":"Scenario","steps":[{"result":{"duration":1060684600,"status":"passed"},"line":38,"name":"User click on remove option of card section","match":{"location":"tek.capstone.bdd.framework.steps.RetailAccountSteps.userClickOnRemoveOptionOfCard()"},"keyword":"And "},{"result":{"duration":16996300,"status":"passed"},"line":39,"name":"payment details should be removed","match":{"location":"tek.capstone.bdd.framework.steps.RetailAccountSteps.paymentDetailsShouldBeRemoved()"},"keyword":"Then "}],"tags":[{"name":"@jenkins"},{"name":"@account5"}]},{"line":4,"name":"","description":"","type":"background","keyword":"Background","steps":[{"result":{"duration":30509900,"status":"passed"},"line":5,"name":"User is on retail website","match":{"location":"tek.capstone.bdd.framework.steps.SignInSteps.userIsOnRetailWebsite()"},"keyword":"Given "},{"result":{"duration":289497200,"status":"passed"},"line":6,"name":"User click on Sign in option","match":{"location":"tek.capstone.bdd.framework.steps.SignInSteps.userClickOnSignIn()"},"keyword":"When "},{"result":{"duration":116385600,"status":"passed"},"line":7,"name":"User enter email 'email' and password 'password'","match":{"arguments":[{"val":"'email'","offset":17},{"val":"'password'","offset":38}],"location":"tek.capstone.bdd.framework.steps.SignInSteps.userEnterEmailAndPassword(java.lang.String,java.lang.String)"},"keyword":"And "},{"result":{"duration":249134800,"status":"passed"},"line":8,"name":"User click on login button","match":{"location":"tek.capstone.bdd.framework.steps.SignInSteps.userClickOnLoginBtn()"},"keyword":"And "},{"result":{"duration":73508200,"status":"passed"},"line":9,"name":"User should be logged in into Account","match":{"location":"tek.capstone.bdd.framework.steps.SignInSteps.userShouldBeLoggedIn()"},"keyword":"And "},{"result":{"duration":261751900,"status":"passed"},"line":10,"name":"User click on Account option","match":{"location":"tek.capstone.bdd.framework.steps.RetailAccountSteps.userClickOnAccountOption()"},"keyword":"When "}]},{"start_timestamp":"2023-03-10T17:49:23.624Z","before":[{"result":{"duration":3038870500,"status":"passed"},"match":{"location":"tek.capstone.bdd.framework.base.BaseUITest.setupTest()"}}],"line":42,"name":"Verify User can add an Address","description":"","id":"retail-account-page;verify-user-can-add-an-address","after":[{"result":{"duration":638429600,"status":"passed"},"match":{"location":"tek.capstone.bdd.framework.base.BaseUITest.closeTest(io.cucumber.java.Scenario)"}}],"type":"scenario","keyword":"Scenario","steps":[{"result":{"duration":240547200,"status":"passed"},"line":43,"name":"User click on Add address option","match":{"location":"tek.capstone.bdd.framework.steps.RetailAccountSteps.userClickOnAddAddressOption()"},"keyword":"And "},{"result":{"duration":812510100,"status":"passed"},"line":44,"name":"User fill new address form with below information","match":{"location":"tek.capstone.bdd.framework.steps.RetailAccountSteps.userFillAddressInfo(io.cucumber.datatable.DataTable)"},"rows":[{"cells":["country","fullName","phoneNumber","streetAddress","apt","city","state","zipCode"]},{"cells":["Canada","fullName","phoneNumber","streetAddress","123","city","Ontario","zipCode"]}],"keyword":"And "},{"result":{"duration":245586100,"status":"passed"},"line":47,"name":"User click Add Your Address button","match":{"location":"tek.capstone.bdd.framework.steps.RetailAccountSteps.userClickAddYourAddressBtn()"},"keyword":"And "},{"result":{"duration":558318900,"status":"passed"},"line":48,"name":"a message should be displayed ‘Address Added Successfully’","match":{"location":"tek.capstone.bdd.framework.steps.RetailAccountSteps.addressAddedMessage()"},"keyword":"Then "}],"tags":[{"name":"@jenkins"},{"name":"@account6"}]},{"line":4,"name":"","description":"","type":"background","keyword":"Background","steps":[{"result":{"duration":39067400,"status":"passed"},"line":5,"name":"User is on retail website","match":{"location":"tek.capstone.bdd.framework.steps.SignInSteps.userIsOnRetailWebsite()"},"keyword":"Given "},{"result":{"duration":304570500,"status":"passed"},"line":6,"name":"User click on Sign in option","match":{"location":"tek.capstone.bdd.framework.steps.SignInSteps.userClickOnSignIn()"},"keyword":"When "},{"result":{"duration":102719800,"status":"passed"},"line":7,"name":"User enter email 'email' and password 'password'","match":{"arguments":[{"val":"'email'","offset":17},{"val":"'password'","offset":38}],"location":"tek.capstone.bdd.framework.steps.SignInSteps.userEnterEmailAndPassword(java.lang.String,java.lang.String)"},"keyword":"And "},{"result":{"duration":254236900,"status":"passed"},"line":8,"name":"User click on login button","match":{"location":"tek.capstone.bdd.framework.steps.SignInSteps.userClickOnLoginBtn()"},"keyword":"And "},{"result":{"duration":51184100,"status":"passed"},"line":9,"name":"User should be logged in into Account","match":{"location":"tek.capstone.bdd.framework.steps.SignInSteps.userShouldBeLoggedIn()"},"keyword":"And "},{"result":{"duration":254843800,"status":"passed"},"line":10,"name":"User click on Account option","match":{"location":"tek.capstone.bdd.framework.steps.RetailAccountSteps.userClickOnAccountOption()"},"keyword":"When "}]},{"start_timestamp":"2023-03-10T17:49:30.193Z","before":[{"result":{"duration":2965173800,"status":"passed"},"match":{"location":"tek.capstone.bdd.framework.base.BaseUITest.setupTest()"}}],"line":51,"name":"Verify User can edit an Address added on account","description":"","id":"retail-account-page;verify-user-can-edit-an-address-added-on-account","after":[{"result":{"duration":629978600,"status":"passed"},"match":{"location":"tek.capstone.bdd.framework.base.BaseUITest.closeTest(io.cucumber.java.Scenario)"}}],"type":"scenario","keyword":"Scenario","steps":[{"result":{"duration":348251000,"status":"passed"},"line":52,"name":"User click on edit address option","match":{"location":"tek.capstone.bdd.framework.steps.RetailAccountSteps.userClickEditOnAddress()"},"keyword":"And "},{"result":{"duration":431953200,"status":"passed"},"line":53,"name":"User fill new address form with below information","match":{"location":"tek.capstone.bdd.framework.steps.RetailAccountSteps.userFillAddressInfo(io.cucumber.datatable.DataTable)"},"rows":[{"cells":["country","fullName","phoneNumber","streetAddress","apt","city","state","zipCode"]},{"cells":["United States","fullName","phoneNumber","streetAddress","123","city","California","zipCode"]}],"keyword":"And "},{"result":{"duration":263843300,"status":"passed"},"line":56,"name":"User click update Your Address button","match":{"location":"tek.capstone.bdd.framework.steps.RetailAccountSteps.userClickOnUpdateYourAddressBtn()"},"keyword":"And "},{"result":{"duration":550378100,"status":"passed"},"line":57,"name":"a message should be displayed Address Updated Successfully","match":{"location":"tek.capstone.bdd.framework.steps.RetailAccountSteps.addressUpdatedMessageShouldBeDisplayed()"},"keyword":"Then "}],"tags":[{"name":"@jenkins"},{"name":"@account7"}]},{"line":4,"name":"","description":"","type":"background","keyword":"Background","steps":[{"result":{"duration":38759700,"status":"passed"},"line":5,"name":"User is on retail website","match":{"location":"tek.capstone.bdd.framework.steps.SignInSteps.userIsOnRetailWebsite()"},"keyword":"Given "},{"result":{"duration":277074900,"status":"passed"},"line":6,"name":"User click on Sign in option","match":{"location":"tek.capstone.bdd.framework.steps.SignInSteps.userClickOnSignIn()"},"keyword":"When "},{"result":{"duration":114049800,"status":"passed"},"line":7,"name":"User enter email 'email' and password 'password'","match":{"arguments":[{"val":"'email'","offset":17},{"val":"'password'","offset":38}],"location":"tek.capstone.bdd.framework.steps.SignInSteps.userEnterEmailAndPassword(java.lang.String,java.lang.String)"},"keyword":"And "},{"result":{"duration":240938300,"status":"passed"},"line":8,"name":"User click on login button","match":{"location":"tek.capstone.bdd.framework.steps.SignInSteps.userClickOnLoginBtn()"},"keyword":"And "},{"result":{"duration":47525400,"status":"passed"},"line":9,"name":"User should be logged in into Account","match":{"location":"tek.capstone.bdd.framework.steps.SignInSteps.userShouldBeLoggedIn()"},"keyword":"And "},{"result":{"duration":269995200,"status":"passed"},"line":10,"name":"User click on Account option","match":{"location":"tek.capstone.bdd.framework.steps.RetailAccountSteps.userClickOnAccountOption()"},"keyword":"When "}]},{"start_timestamp":"2023-03-10T17:49:36.401Z","before":[{"result":{"duration":2991160900,"status":"passed"},"match":{"location":"tek.capstone.bdd.framework.base.BaseUITest.setupTest()"}}],"line":60,"name":"Verify User can remove Address from Account","description":"","id":"retail-account-page;verify-user-can-remove-address-from-account","after":[{"result":{"duration":689310000,"status":"passed"},"match":{"location":"tek.capstone.bdd.framework.base.BaseUITest.closeTest(io.cucumber.java.Scenario)"}}],"type":"scenario","keyword":"Scenario","steps":[{"result":{"duration":254910600,"status":"passed"},"line":61,"name":"User click on remove option of Address section","match":{"location":"tek.capstone.bdd.framework.steps.RetailAccountSteps.userClickRemoveOnAddress()"},"keyword":"And "},{"result":{"duration":14997400,"status":"passed"},"line":62,"name":"Address details should be removed","match":{"location":"tek.capstone.bdd.framework.steps.RetailAccountSteps.addressDetailsShouldBeRemoved()"},"keyword":"Then "}],"tags":[{"name":"@jenkins"},{"name":"@account8"}]}],"name":"Retail Account Page","description":"","id":"retail-account-page","keyword":"Feature","uri":"classpath:features/RetailAccount.feature","tags":[{"name":"@jenkins","type":"Tag","location":{"line":1,"column":1}}]},{"line":2,"elements":[{"line":4,"name":"","description":"","type":"background","keyword":"Background","steps":[{"result":{"duration":41621700,"status":"passed"},"line":5,"name":"User is on retail website","match":{"location":"tek.capstone.bdd.framework.steps.SignInSteps.userIsOnRetailWebsite()"},"keyword":"Given "},{"result":{"duration":309934100,"status":"passed"},"line":6,"name":"User click on Sign in option","match":{"location":"tek.capstone.bdd.framework.steps.SignInSteps.userClickOnSignIn()"},"keyword":"When "},{"result":{"duration":96907100,"status":"passed"},"line":7,"name":"User enter email 'email' and password 'password'","match":{"arguments":[{"val":"'email'","offset":17},{"val":"'password'","offset":38}],"location":"tek.capstone.bdd.framework.steps.SignInSteps.userEnterEmailAndPassword(java.lang.String,java.lang.String)"},"keyword":"And "},{"result":{"duration":252267200,"status":"passed"},"line":8,"name":"User click on login button","match":{"location":"tek.capstone.bdd.framework.steps.SignInSteps.userClickOnLoginBtn()"},"keyword":"And "},{"result":{"duration":38738800,"status":"passed"},"line":9,"name":"User should be logged in into Account","match":{"location":"tek.capstone.bdd.framework.steps.SignInSteps.userShouldBeLoggedIn()"},"keyword":"And "},{"result":{"duration":252024700,"status":"passed"},"line":10,"name":"User click on Orders section","match":{"location":"tek.capstone.bdd.framework.steps.RetailOrderSteps.userClickOnOrdersSection()"},"keyword":"And "},{"result":{"duration":163739500,"status":"passed"},"line":11,"name":"User click on first order in list","match":{"location":"tek.capstone.bdd.framework.steps.RetailOrderSteps.userClickOnFirstOrderInList()"},"keyword":"And "}]},{"start_timestamp":"2023-03-10T17:49:41.353Z","before":[{"result":{"duration":3040328400,"status":"passed"},"match":{"location":"tek.capstone.bdd.framework.base.BaseUITest.setupTest()"}}],"line":14,"name":"Verify User can cancel the order","description":"","id":"retail-order-page;verify-user-can-cancel-the-order","after":[{"result":{"duration":630068300,"status":"passed"},"match":{"location":"tek.capstone.bdd.framework.base.BaseUITest.closeTest(io.cucumber.java.Scenario)"}}],"type":"scenario","keyword":"Scenario","steps":[{"result":{"duration":254174600,"status":"passed"},"line":15,"name":"User click on Cancel The Order button","match":{"location":"tek.capstone.bdd.framework.steps.RetailOrderSteps.userClickOnCancelTheOrderBtn()"},"keyword":"And "},{"result":{"duration":244067700,"status":"passed"},"line":16,"name":"User select the cancelation Reason 'Bought wrong item'","match":{"arguments":[{"val":"'Bought wrong item'","offset":35}],"location":"tek.capstone.bdd.framework.steps.RetailOrderSteps.userSelectTheCancellationReason(java.lang.String)"},"keyword":"And "},{"result":{"duration":235080900,"status":"passed"},"line":17,"name":"User click on Cancel Order button","match":{"location":"tek.capstone.bdd.framework.steps.RetailOrderSteps.userClickOnCancelOrderbutton()"},"keyword":"And "},{"result":{"duration":25987900,"status":"passed"},"line":18,"name":"a cancelation message should be displayed 'Your Order Has Been Cancelled'","match":{"arguments":[{"val":"'Your Order Has Been Cancelled'","offset":42}],"location":"tek.capstone.bdd.framework.steps.RetailOrderSteps.cancellationMessageShouldBeDisplayed(java.lang.String)"},"keyword":"Then "}],"tags":[{"name":"@jenkins"},{"name":"@order1"}]},{"line":4,"name":"","description":"","type":"background","keyword":"Background","steps":[{"result":{"duration":38488200,"status":"passed"},"line":5,"name":"User is on retail website","match":{"location":"tek.capstone.bdd.framework.steps.SignInSteps.userIsOnRetailWebsite()"},"keyword":"Given "},{"result":{"duration":286132200,"status":"passed"},"line":6,"name":"User click on Sign in option","match":{"location":"tek.capstone.bdd.framework.steps.SignInSteps.userClickOnSignIn()"},"keyword":"When "},{"result":{"duration":115296200,"status":"passed"},"line":7,"name":"User enter email 'email' and password 'password'","match":{"arguments":[{"val":"'email'","offset":17},{"val":"'password'","offset":38}],"location":"tek.capstone.bdd.framework.steps.SignInSteps.userEnterEmailAndPassword(java.lang.String,java.lang.String)"},"keyword":"And "},{"result":{"duration":241159300,"status":"passed"},"line":8,"name":"User click on login button","match":{"location":"tek.capstone.bdd.framework.steps.SignInSteps.userClickOnLoginBtn()"},"keyword":"And "},{"result":{"duration":67292300,"status":"passed"},"line":9,"name":"User should be logged in into Account","match":{"location":"tek.capstone.bdd.framework.steps.SignInSteps.userShouldBeLoggedIn()"},"keyword":"And "},{"result":{"duration":251137600,"status":"passed"},"line":10,"name":"User click on Orders section","match":{"location":"tek.capstone.bdd.framework.steps.RetailOrderSteps.userClickOnOrdersSection()"},"keyword":"And "},{"result":{"duration":38585100,"status":"passed"},"line":11,"name":"User click on first order in list","match":{"location":"tek.capstone.bdd.framework.steps.RetailOrderSteps.userClickOnFirstOrderInList()"},"keyword":"And "}]},{"start_timestamp":"2023-03-10T17:49:46.949Z","before":[{"result":{"duration":2977989900,"status":"passed"},"match":{"location":"tek.capstone.bdd.framework.base.BaseUITest.setupTest()"}}],"line":21,"name":"Verify User can Return the order","description":"","id":"retail-order-page;verify-user-can-return-the-order","after":[{"result":{"duration":636426300,"status":"passed"},"match":{"location":"tek.capstone.bdd.framework.base.BaseUITest.closeTest(io.cucumber.java.Scenario)"}}],"type":"scenario","keyword":"Scenario","steps":[{"result":{"duration":6084752400,"status":"passed"},"line":22,"name":"User click on Return Items button","match":{"location":"tek.capstone.bdd.framework.steps.RetailOrderSteps.userClickOnReturnItemsButton()"},"keyword":"And "},{"result":{"duration":261893400,"status":"passed"},"line":23,"name":"User select the Return Reason 'Item damaged'","match":{"arguments":[{"val":"'Item damaged'","offset":30}],"location":"tek.capstone.bdd.framework.steps.RetailOrderSteps.userSelectReturnReason(java.lang.String)"},"keyword":"And "},{"result":{"duration":232909400,"status":"passed"},"line":24,"name":"User select the drop off service 'FedEx'","match":{"arguments":[{"val":"'FedEx'","offset":33}],"location":"tek.capstone.bdd.framework.steps.RetailOrderSteps.userSelectDropOffService(java.lang.String)"},"keyword":"And "},{"result":{"duration":261563200,"status":"passed"},"line":25,"name":"User click on Return Order button","match":{"location":"tek.capstone.bdd.framework.steps.RetailOrderSteps.userClickOnReturnOrderBtn()"},"keyword":"And "},{"result":{"duration":19046300,"status":"passed"},"line":26,"name":"a cancelation message should be displayed 'Return was successfull'","match":{"arguments":[{"val":"'Return was successfull'","offset":42}],"location":"tek.capstone.bdd.framework.steps.RetailOrderSteps.cancellationMessageShouldBeDisplayed(java.lang.String)"},"keyword":"Then "}],"tags":[{"name":"@jenkins"},{"name":"@order2"}]},{"line":4,"name":"","description":"","type":"background","keyword":"Background","steps":[{"result":{"duration":44748200,"status":"passed"},"line":5,"name":"User is on retail website","match":{"location":"tek.capstone.bdd.framework.steps.SignInSteps.userIsOnRetailWebsite()"},"keyword":"Given "},{"result":{"duration":290587300,"status":"passed"},"line":6,"name":"User click on Sign in option","match":{"location":"tek.capstone.bdd.framework.steps.SignInSteps.userClickOnSignIn()"},"keyword":"When "},{"result":{"duration":112487000,"status":"passed"},"line":7,"name":"User enter email 'email' and password 'password'","match":{"arguments":[{"val":"'email'","offset":17},{"val":"'password'","offset":38}],"location":"tek.capstone.bdd.framework.steps.SignInSteps.userEnterEmailAndPassword(java.lang.String,java.lang.String)"},"keyword":"And "},{"result":{"duration":244269900,"status":"passed"},"line":8,"name":"User click on login button","match":{"location":"tek.capstone.bdd.framework.steps.SignInSteps.userClickOnLoginBtn()"},"keyword":"And "},{"result":{"duration":193420800,"status":"passed"},"line":9,"name":"User should be logged in into Account","match":{"location":"tek.capstone.bdd.framework.steps.SignInSteps.userShouldBeLoggedIn()"},"keyword":"And "},{"result":{"duration":246548500,"status":"passed"},"line":10,"name":"User click on Orders section","match":{"location":"tek.capstone.bdd.framework.steps.RetailOrderSteps.userClickOnOrdersSection()"},"keyword":"And "},{"result":{"duration":50861000,"status":"passed"},"line":11,"name":"User click on first order in list","match":{"location":"tek.capstone.bdd.framework.steps.RetailOrderSteps.userClickOnFirstOrderInList()"},"keyword":"And "}]},{"start_timestamp":"2023-03-10T17:49:58.475Z","before":[{"result":{"duration":2946992400,"status":"passed"},"match":{"location":"tek.capstone.bdd.framework.base.BaseUITest.setupTest()"}}],"line":29,"name":"Verify User can write a review on order placed","description":"","id":"retail-order-page;verify-user-can-write-a-review-on-order-placed","after":[{"result":{"duration":639794100,"status":"passed"},"match":{"location":"tek.capstone.bdd.framework.base.BaseUITest.closeTest(io.cucumber.java.Scenario)"}}],"type":"scenario","keyword":"Scenario","steps":[{"result":{"duration":244120200,"status":"passed"},"line":30,"name":"User click on Review button","match":{"location":"tek.capstone.bdd.framework.steps.RetailOrderSteps.userClickOnReviewBtn()"},"keyword":"And "},{"result":{"duration":114844600,"status":"passed"},"line":31,"name":"User write Review headline 'Good product' and 'the product quality was good'","match":{"arguments":[{"val":"'Good product'","offset":27},{"val":"'the product quality was good'","offset":46}],"location":"tek.capstone.bdd.framework.steps.RetailOrderSteps.userWriteReviewHeadlineAndText(java.lang.String,java.lang.String)"},"keyword":"And "},{"result":{"duration":267799900,"status":"passed"},"line":32,"name":"User click Add your Review button","match":{"location":"tek.capstone.bdd.framework.steps.RetailOrderSteps.userClickAddYourReviewButton()"},"keyword":"And "},{"result":{"duration":544840000,"status":"passed"},"line":33,"name":"a review message should be displayed 'Your review was added successfully'","match":{"arguments":[{"val":"'Your review was added successfully'","offset":37}],"location":"tek.capstone.bdd.framework.steps.RetailOrderSteps.reviewMessageShouldBeDisplayed(java.lang.String)"},"keyword":"Then "}],"tags":[{"name":"@jenkins"},{"name":"@order3"}]}],"name":"Retail Order Page","description":"","id":"retail-order-page","keyword":"Feature","uri":"classpath:features/RetailOrder.feature","tags":[{"name":"@jenkins","type":"Tag","location":{"line":1,"column":1}}]},{"line":2,"elements":[{"line":4,"name":"","description":"","type":"background","keyword":"Background","steps":[{"result":{"duration":39034600,"status":"passed"},"line":5,"name":"User is on retail website","match":{"location":"tek.capstone.bdd.framework.steps.SignInSteps.userIsOnRetailWebsite()"},"keyword":"Given "},{"result":{"duration":293916000,"status":"passed"},"line":6,"name":"User click on Sign in option","match":{"location":"tek.capstone.bdd.framework.steps.SignInSteps.userClickOnSignIn()"},"keyword":"When "}]},{"start_timestamp":"2023-03-10T17:50:04.430Z","before":[{"result":{"duration":2897600400,"status":"passed"},"match":{"location":"tek.capstone.bdd.framework.base.BaseUITest.setupTest()"}}],"line":9,"name":"Verify user can sign in into Retail Application","description":"","id":"sign-in-feature;verify-user-can-sign-in-into-retail-application","after":[{"result":{"duration":634401300,"status":"passed"},"match":{"location":"tek.capstone.bdd.framework.base.BaseUITest.closeTest(io.cucumber.java.Scenario)"}}],"type":"scenario","keyword":"Scenario","steps":[{"result":{"duration":131439000,"status":"passed"},"line":10,"name":"User enter email \"email\" and password \"password\"","match":{"arguments":[{"val":"\"email\"","offset":17},{"val":"\"password\"","offset":38}],"location":"tek.capstone.bdd.framework.steps.SignInSteps.userEnterEmailAndPassword(java.lang.String,java.lang.String)"},"keyword":"And "},{"result":{"duration":241410100,"status":"passed"},"line":11,"name":"User click on login button","match":{"location":"tek.capstone.bdd.framework.steps.SignInSteps.userClickOnLoginBtn()"},"keyword":"And "},{"result":{"duration":46572200,"status":"passed"},"line":12,"name":"User should be logged in into Account","match":{"location":"tek.capstone.bdd.framework.steps.SignInSteps.userShouldBeLoggedIn()"},"keyword":"Then "}],"tags":[{"name":"@jenkins"},{"name":"@signIn1"}]},{"line":4,"name":"","description":"","type":"background","keyword":"Background","steps":[{"result":{"duration":38885000,"status":"passed"},"line":5,"name":"User is on retail website","match":{"location":"tek.capstone.bdd.framework.steps.SignInSteps.userIsOnRetailWebsite()"},"keyword":"Given "},{"result":{"duration":289272000,"status":"passed"},"line":6,"name":"User click on Sign in option","match":{"location":"tek.capstone.bdd.framework.steps.SignInSteps.userClickOnSignIn()"},"keyword":"When "}]},{"start_timestamp":"2023-03-10T17:50:08.721Z","before":[{"result":{"duration":2970078000,"status":"passed"},"match":{"location":"tek.capstone.bdd.framework.base.BaseUITest.setupTest()"}}],"line":15,"name":"Verify user can create an account into Retail Website","description":"","id":"sign-in-feature;verify-user-can-create-an-account-into-retail-website","after":[{"result":{"duration":626883100,"status":"passed"},"match":{"location":"tek.capstone.bdd.framework.base.BaseUITest.closeTest(io.cucumber.java.Scenario)"}}],"type":"scenario","keyword":"Scenario","steps":[{"result":{"duration":261238900,"status":"passed"},"line":16,"name":"User click on Create New Account button","match":{"location":"tek.capstone.bdd.framework.steps.SignInSteps.userClickOnNewAccountBtn()"},"keyword":"And "},{"result":{"duration":205397700,"status":"passed"},"line":17,"name":"User fill the signUp information with below data","match":{"location":"tek.capstone.bdd.framework.steps.SignInSteps.userFillTheSignUpForm(io.cucumber.datatable.DataTable)"},"rows":[{"cells":["name","email","password","confirmPassword"]},{"cells":["fullName","email","Tek@12345","Tek@12345"]}],"keyword":"And "},{"result":{"duration":248635100,"status":"passed"},"line":20,"name":"User click on SignUp button","match":{"location":"tek.capstone.bdd.framework.steps.SignInSteps.userClickOnSignUpBtn()"},"keyword":"And "},{"result":{"duration":491414300,"status":"passed"},"line":21,"name":"User should be logged into account page","match":{"location":"tek.capstone.bdd.framework.steps.SignInSteps.userShouldBeLoggedIntoAccount()"},"keyword":"Then "}],"tags":[{"name":"@jenkins"},{"name":"@signIn"}]}],"name":"Sign In Feature","description":"","id":"sign-in-feature","keyword":"Feature","uri":"classpath:features/SignIn.feature","tags":[{"name":"@jenkins","type":"Tag","location":{"line":1,"column":1}}]}]