[{"line":2,"elements":[{"line":4,"name":"","description":"","type":"background","keyword":"Background","steps":[{"result":{"duration":96299600,"status":"passed"},"line":5,"name":"User is on retail website","match":{"location":"tek.capstone.bdd.framework.steps.SignInSteps.userIsOnRetailWebsite()"},"keyword":"Given "}]},{"start_timestamp":"2023-03-24T18:00:36.005Z","before":[{"result":{"duration":3099259000,"status":"passed"},"match":{"location":"tek.capstone.bdd.framework.base.BaseUITest.setupTest()"}}],"line":22,"name":"Verify department sidebar options","description":"","id":"retail-home-page;verify-department-sidebar-options;;2","after":[{"result":{"duration":609494800,"status":"passed"},"match":{"location":"tek.capstone.bdd.framework.base.BaseUITest.closeTest(io.cucumber.java.Scenario)"}}],"type":"scenario","keyword":"Scenario Outline","steps":[{"result":{"duration":149917400,"status":"passed"},"line":15,"name":"User click on All section","match":{"location":"tek.capstone.bdd.framework.steps.HomeSteps.userClickOnAllSection()"},"keyword":"When "},{"result":{"duration":103050000,"status":"passed"},"line":16,"name":"User on 'Electronics'","match":{"arguments":[{"val":"'Electronics'","offset":8}],"location":"tek.capstone.bdd.framework.steps.HomeSteps.userOnDepartment(java.lang.String)"},"keyword":"And "},{"result":{"duration":128100700,"status":"passed"},"line":17,"name":"below options are present in department","match":{"location":"tek.capstone.bdd.framework.steps.HomeSteps.belowOptionsArePresentInDepartment(io.cucumber.datatable.DataTable)"},"rows":[{"cells":["TV & Video","Video Games"]}],"keyword":"Then "}],"tags":[{"name":"@jenkins"},{"name":"@home2"},{"name":"@smoke"}]},{"line":4,"name":"","description":"","type":"background","keyword":"Background","steps":[{"result":{"duration":51791700,"status":"passed"},"line":5,"name":"User is on retail website","match":{"location":"tek.capstone.bdd.framework.steps.SignInSteps.userIsOnRetailWebsite()"},"keyword":"Given "}]},{"start_timestamp":"2023-03-24T18:00:40.231Z","before":[{"result":{"duration":1935300700,"status":"passed"},"match":{"location":"tek.capstone.bdd.framework.base.BaseUITest.setupTest()"}}],"line":23,"name":"Verify department sidebar options","description":"","id":"retail-home-page;verify-department-sidebar-options;;3","after":[{"result":{"duration":581395300,"status":"passed"},"match":{"location":"tek.capstone.bdd.framework.base.BaseUITest.closeTest(io.cucumber.java.Scenario)"}}],"type":"scenario","keyword":"Scenario Outline","steps":[{"result":{"duration":106454000,"status":"passed"},"line":15,"name":"User click on All section","match":{"location":"tek.capstone.bdd.framework.steps.HomeSteps.userClickOnAllSection()"},"keyword":"When "},{"result":{"duration":88626600,"status":"passed"},"line":16,"name":"User on 'Computers'","match":{"arguments":[{"val":"'Computers'","offset":8}],"location":"tek.capstone.bdd.framework.steps.HomeSteps.userOnDepartment(java.lang.String)"},"keyword":"And "},{"result":{"duration":84589400,"status":"passed"},"line":17,"name":"below options are present in department","match":{"location":"tek.capstone.bdd.framework.steps.HomeSteps.belowOptionsArePresentInDepartment(io.cucumber.datatable.DataTable)"},"rows":[{"cells":["Accessories","Networking"]}],"keyword":"Then "}],"tags":[{"name":"@jenkins"},{"name":"@home2"},{"name":"@smoke"}]},{"line":4,"name":"","description":"","type":"background","keyword":"Background","steps":[{"result":{"duration":47319900,"status":"passed"},"line":5,"name":"User is on retail website","match":{"location":"tek.capstone.bdd.framework.steps.SignInSteps.userIsOnRetailWebsite()"},"keyword":"Given "}]},{"start_timestamp":"2023-03-24T18:00:43.088Z","before":[{"result":{"duration":1967504000,"status":"passed"},"match":{"location":"tek.capstone.bdd.framework.base.BaseUITest.setupTest()"}}],"line":24,"name":"Verify department sidebar options","description":"","id":"retail-home-page;verify-department-sidebar-options;;4","after":[{"result":{"duration":606963400,"status":"passed"},"match":{"location":"tek.capstone.bdd.framework.base.BaseUITest.closeTest(io.cucumber.java.Scenario)"}}],"type":"scenario","keyword":"Scenario Outline","steps":[{"result":{"duration":103784800,"status":"passed"},"line":15,"name":"User click on All section","match":{"location":"tek.capstone.bdd.framework.steps.HomeSteps.userClickOnAllSection()"},"keyword":"When "},{"result":{"duration":101332900,"status":"passed"},"line":16,"name":"User on 'Smart Home'","match":{"arguments":[{"val":"'Smart Home'","offset":8}],"location":"tek.capstone.bdd.framework.steps.HomeSteps.userOnDepartment(java.lang.String)"},"keyword":"And "},{"result":{"duration":83729500,"status":"passed"},"line":17,"name":"below options are present in department","match":{"location":"tek.capstone.bdd.framework.steps.HomeSteps.belowOptionsArePresentInDepartment(io.cucumber.datatable.DataTable)"},"rows":[{"cells":["Smart Home Lightning","Plugs and Outlets"]}],"keyword":"Then "}],"tags":[{"name":"@jenkins"},{"name":"@home2"},{"name":"@smoke"}]},{"line":4,"name":"","description":"","type":"background","keyword":"Background","steps":[{"result":{"duration":38283800,"status":"passed"},"line":5,"name":"User is on retail website","match":{"location":"tek.capstone.bdd.framework.steps.SignInSteps.userIsOnRetailWebsite()"},"keyword":"Given "}]},{"start_timestamp":"2023-03-24T18:00:46.011Z","before":[{"result":{"duration":1889017000,"status":"passed"},"match":{"location":"tek.capstone.bdd.framework.base.BaseUITest.setupTest()"}}],"line":25,"name":"Verify department sidebar options","description":"","id":"retail-home-page;verify-department-sidebar-options;;5","after":[{"result":{"duration":613205500,"status":"passed"},"match":{"location":"tek.capstone.bdd.framework.base.BaseUITest.closeTest(io.cucumber.java.Scenario)"}}],"type":"scenario","keyword":"Scenario Outline","steps":[{"result":{"duration":104121500,"status":"passed"},"line":15,"name":"User click on All section","match":{"location":"tek.capstone.bdd.framework.steps.HomeSteps.userClickOnAllSection()"},"keyword":"When "},{"result":{"duration":122906500,"status":"passed"},"line":16,"name":"User on 'Sports'","match":{"arguments":[{"val":"'Sports'","offset":8}],"location":"tek.capstone.bdd.framework.steps.HomeSteps.userOnDepartment(java.lang.String)"},"keyword":"And "},{"result":{"duration":110400100,"status":"passed"},"line":17,"name":"below options are present in department","match":{"location":"tek.capstone.bdd.framework.steps.HomeSteps.belowOptionsArePresentInDepartment(io.cucumber.datatable.DataTable)"},"rows":[{"cells":["Athletic Clothing","Exercise & Fitness"]}],"keyword":"Then "}],"tags":[{"name":"@jenkins"},{"name":"@home2"},{"name":"@smoke"}]},{"line":4,"name":"","description":"","type":"background","keyword":"Background","steps":[{"result":{"duration":45666600,"status":"passed"},"line":5,"name":"User is on retail website","match":{"location":"tek.capstone.bdd.framework.steps.SignInSteps.userIsOnRetailWebsite()"},"keyword":"Given "}]},{"start_timestamp":"2023-03-24T18:00:48.894Z","before":[{"result":{"duration":1853761300,"status":"passed"},"match":{"location":"tek.capstone.bdd.framework.base.BaseUITest.setupTest()"}}],"line":26,"name":"Verify department sidebar options","description":"","id":"retail-home-page;verify-department-sidebar-options;;6","after":[{"result":{"duration":602355600,"status":"passed"},"match":{"location":"tek.capstone.bdd.framework.base.BaseUITest.closeTest(io.cucumber.java.Scenario)"}}],"type":"scenario","keyword":"Scenario Outline","steps":[{"result":{"duration":104498100,"status":"passed"},"line":15,"name":"User click on All section","match":{"location":"tek.capstone.bdd.framework.steps.HomeSteps.userClickOnAllSection()"},"keyword":"When "},{"result":{"duration":91689600,"status":"passed"},"line":16,"name":"User on 'Automotive'","match":{"arguments":[{"val":"'Automotive'","offset":8}],"location":"tek.capstone.bdd.framework.steps.HomeSteps.userOnDepartment(java.lang.String)"},"keyword":"And "},{"result":{"duration":62810200,"status":"passed"},"line":17,"name":"below options are present in department","match":{"location":"tek.capstone.bdd.framework.steps.HomeSteps.belowOptionsArePresentInDepartment(io.cucumber.datatable.DataTable)"},"rows":[{"cells":["Automative Parts & Accessories","MotorCycle & Powersports"]}],"keyword":"Then "}],"tags":[{"name":"@jenkins"},{"name":"@home2"},{"name":"@smoke"}]},{"line":4,"name":"","description":"","type":"background","keyword":"Background","steps":[{"result":{"duration":63032900,"status":"passed"},"line":5,"name":"User is on retail website","match":{"location":"tek.capstone.bdd.framework.steps.SignInSteps.userIsOnRetailWebsite()"},"keyword":"Given "}]},{"start_timestamp":"2023-03-24T18:00:51.674Z","before":[{"result":{"duration":1747526500,"status":"passed"},"match":{"location":"tek.capstone.bdd.framework.base.BaseUITest.setupTest()"}}],"line":44,"name":"Verify User can place an order without Shipping address and payment Method on file","description":"","id":"retail-home-page;verify-user-can-place-an-order-without-shipping-address-and-payment-method-on-file","after":[{"result":{"duration":610037200,"status":"passed"},"match":{"location":"tek.capstone.bdd.framework.base.BaseUITest.closeTest(io.cucumber.java.Scenario)"}}],"type":"scenario","keyword":"Scenario","steps":[{"result":{"duration":78122700,"status":"passed"},"line":45,"name":"User click on Sign in option","match":{"location":"tek.capstone.bdd.framework.steps.SignInSteps.userClickOnSignIn()"},"keyword":"When "},{"result":{"duration":178468100,"status":"passed"},"line":46,"name":"User enter email 'email' and password 'password'","match":{"arguments":[{"val":"'email'","offset":17},{"val":"'password'","offset":38}],"location":"tek.capstone.bdd.framework.steps.SignInSteps.userEnterEmailAndPassword(java.lang.String,java.lang.String)"},"keyword":"And "},{"result":{"duration":57847100,"status":"passed"},"line":47,"name":"User click on login button","match":{"location":"tek.capstone.bdd.framework.steps.SignInSteps.userClickOnLoginBtn()"},"keyword":"And "},{"result":{"duration":262409100,"status":"passed"},"line":48,"name":"User should be logged in into Account","match":{"location":"tek.capstone.bdd.framework.steps.SignInSteps.userShouldBeLoggedIn()"},"keyword":"And "},{"result":{"duration":214584600,"status":"passed"},"line":49,"name":"User change the category to 'Smart Home'","match":{"arguments":[{"val":"'Smart Home'","offset":28}],"location":"tek.capstone.bdd.framework.steps.HomeSteps.userChangeCategory(java.lang.String)"},"keyword":"And "},{"result":{"duration":79886000,"status":"passed"},"line":50,"name":"User search for an item 'kasa outdoor smart plug'","match":{"arguments":[{"val":"'kasa outdoor smart plug'","offset":24}],"location":"tek.capstone.bdd.framework.steps.HomeSteps.userSearchForAnItem(java.lang.String)"},"keyword":"And "},{"result":{"duration":75982700,"status":"passed"},"line":51,"name":"User click on Search icon","match":{"location":"tek.capstone.bdd.framework.steps.HomeSteps.userClickOnSearchIcon()"},"keyword":"And "},{"result":{"duration":205205900,"status":"passed"},"line":52,"name":"User click on item","match":{"location":"tek.capstone.bdd.framework.steps.HomeSteps.userClickOnItem()"},"keyword":"And "},{"result":{"duration":182380400,"status":"passed"},"line":53,"name":"User select quantity '2'","match":{"arguments":[{"val":"'2'","offset":21}],"location":"tek.capstone.bdd.framework.steps.HomeSteps.userSelectQuantity(java.lang.String)"},"keyword":"And "},{"result":{"duration":52033900,"status":"passed"},"line":54,"name":"User click add to Cart button","match":{"location":"tek.capstone.bdd.framework.steps.HomeSteps.userClickOnAddToCartBtn()"},"keyword":"And "},{"result":{"duration":344347700,"status":"passed"},"line":55,"name":"the cart icon quantity should change to '2'","match":{"arguments":[{"val":"'2'","offset":40}],"location":"tek.capstone.bdd.framework.steps.HomeSteps.theCartIconShouldChange(java.lang.String)"},"keyword":"Then "},{"result":{"duration":39068000,"status":"passed"},"line":56,"name":"User click on Cart option","match":{"location":"tek.capstone.bdd.framework.steps.HomeSteps.userClickOnCartOption()"},"keyword":"And "},{"result":{"duration":103186200,"status":"passed"},"line":57,"name":"User click on Proceed to Checkout button","match":{"location":"tek.capstone.bdd.framework.steps.HomeSteps.userClickOnProceedToCheckoutBtn()"},"keyword":"And "},{"result":{"duration":97448700,"status":"passed"},"line":58,"name":"User click Add a new address link for shipping address","match":{"location":"tek.capstone.bdd.framework.steps.HomeSteps.userClickOnAddANewAddressLink()"},"keyword":"And "},{"result":{"duration":969795400,"status":"passed"},"line":59,"name":"User fill new address form with below information","match":{"location":"tek.capstone.bdd.framework.steps.RetailAccountSteps.userFillAddressInfo(io.cucumber.datatable.DataTable)"},"rows":[{"cells":["country","fullName","phoneNumber","streetAddress","apt","city","state","zipCode"]},{"cells":["United States","fullName","phoneNumber","streetAddress","123","city","California","zipCode"]}],"keyword":"And "},{"result":{"duration":81934100,"status":"passed"},"line":62,"name":"User click Add Your Address button","match":{"location":"tek.capstone.bdd.framework.steps.RetailAccountSteps.userClickAddYourAddressBtn()"},"keyword":"And "},{"result":{"duration":139829800,"status":"passed"},"line":63,"name":"User click Add a credit card or Debit Card for Payment method","match":{"location":"tek.capstone.bdd.framework.steps.HomeSteps.userClickAddACreditOrDebitCardLink()"},"keyword":"And "},{"result":{"duration":339486500,"status":"passed"},"line":64,"name":"User fill Debit or credit card information","match":{"location":"tek.capstone.bdd.framework.steps.RetailAccountSteps.userFillDebitOrCreditCardInfo(io.cucumber.datatable.DataTable)"},"rows":[{"cells":["cardNumber","nameOnCard","expirationMonth","expirationYear","securityCode"]},{"cells":["cardNumber","fullName","4","2024","789"]}],"keyword":"And "},{"result":{"duration":56743200,"status":"passed"},"line":67,"name":"User click on Add your card button","match":{"location":"tek.capstone.bdd.framework.steps.RetailAccountSteps.userClickOnAddYourCardBtn()"},"keyword":"And "},{"result":{"duration":123390800,"status":"passed"},"line":68,"name":"User click on Place Your Order","match":{"location":"tek.capstone.bdd.framework.steps.HomeSteps.userClickOnPlaceYourOrder()"},"keyword":"And "},{"result":{"duration":270498800,"status":"passed"},"line":69,"name":"a message should be displayed ‘Order Placed, Thanks’","match":{"location":"tek.capstone.bdd.framework.steps.HomeSteps.orderPlacedMessageShouldBeDisplayed()"},"keyword":"Then "}],"tags":[{"name":"@jenkins"},{"name":"@home4"},{"name":"@smoke"}]}],"name":"Retail Home Page","description":"","id":"retail-home-page","keyword":"Feature","uri":"classpath:features/Home.feature","tags":[{"name":"@jenkins","type":"Tag","location":{"line":1,"column":1}}]},{"line":2,"elements":[{"line":4,"name":"","description":"","type":"background","keyword":"Background","steps":[{"result":{"duration":44522600,"status":"passed"},"line":5,"name":"User is on retail website","match":{"location":"tek.capstone.bdd.framework.steps.SignInSteps.userIsOnRetailWebsite()"},"keyword":"Given "},{"result":{"duration":136433200,"status":"passed"},"line":6,"name":"User click on Sign in option","match":{"location":"tek.capstone.bdd.framework.steps.SignInSteps.userClickOnSignIn()"},"keyword":"When "},{"result":{"duration":147484500,"status":"passed"},"line":7,"name":"User enter email 'email' and password 'password'","match":{"arguments":[{"val":"'email'","offset":17},{"val":"'password'","offset":38}],"location":"tek.capstone.bdd.framework.steps.SignInSteps.userEnterEmailAndPassword(java.lang.String,java.lang.String)"},"keyword":"And "},{"result":{"duration":55621900,"status":"passed"},"line":8,"name":"User click on login button","match":{"location":"tek.capstone.bdd.framework.steps.SignInSteps.userClickOnLoginBtn()"},"keyword":"And "},{"result":{"duration":257259500,"status":"passed"},"line":9,"name":"User should be logged in into Account","match":{"location":"tek.capstone.bdd.framework.steps.SignInSteps.userShouldBeLoggedIn()"},"keyword":"And "},{"result":{"duration":93086100,"status":"passed"},"line":10,"name":"User click on Account option","match":{"location":"tek.capstone.bdd.framework.steps.RetailAccountSteps.userClickOnAccountOption()"},"keyword":"When "}]},{"start_timestamp":"2023-03-24T18:00:58.065Z","before":[{"result":{"duration":1891106600,"status":"passed"},"match":{"location":"tek.capstone.bdd.framework.base.BaseUITest.setupTest()"}}],"line":50,"name":"Verify User can add an Address","description":"","id":"retail-account-page;verify-user-can-add-an-address","after":[{"result":{"duration":576129300,"status":"passed"},"match":{"location":"tek.capstone.bdd.framework.base.BaseUITest.closeTest(io.cucumber.java.Scenario)"}}],"type":"scenario","keyword":"Scenario","steps":[{"result":{"duration":141244700,"status":"passed"},"line":51,"name":"User click on Add address option","match":{"location":"tek.capstone.bdd.framework.steps.RetailAccountSteps.userClickOnAddAddressOption()"},"keyword":"And "},{"result":{"duration":765076200,"status":"passed"},"line":52,"name":"User fill new address form with below information","match":{"location":"tek.capstone.bdd.framework.steps.RetailAccountSteps.userFillAddressInfo(io.cucumber.datatable.DataTable)"},"rows":[{"cells":["country","fullName","phoneNumber","streetAddress","apt","city","state","zipCode"]},{"cells":["Canada","fullName","phoneNumber","streetAddress","123","city","Ontario","zipCode"]}],"keyword":"And "},{"result":{"duration":78885700,"status":"passed"},"line":55,"name":"User click Add Your Address button","match":{"location":"tek.capstone.bdd.framework.steps.RetailAccountSteps.userClickAddYourAddressBtn()"},"keyword":"And "},{"result":{"duration":701607700,"status":"passed"},"line":56,"name":"a message should be displayed ‘Address Added Successfully’","match":{"location":"tek.capstone.bdd.framework.steps.RetailAccountSteps.addressAddedMessage()"},"keyword":"Then "}],"tags":[{"name":"@jenkins"},{"name":"@account6"},{"name":"@smoke"}]}],"name":"Retail Account Page","description":"","id":"retail-account-page","keyword":"Feature","uri":"classpath:features/RetailAccount.feature","tags":[{"name":"@jenkins","type":"Tag","location":{"line":1,"column":1}}]},{"line":2,"elements":[{"line":4,"name":"","description":"","type":"background","keyword":"Background","steps":[{"result":{"duration":65120700,"status":"passed"},"line":5,"name":"User is on retail website","match":{"location":"tek.capstone.bdd.framework.steps.SignInSteps.userIsOnRetailWebsite()"},"keyword":"Given "},{"result":{"duration":71398600,"status":"passed"},"line":6,"name":"User click on Sign in option","match":{"location":"tek.capstone.bdd.framework.steps.SignInSteps.userClickOnSignIn()"},"keyword":"When "},{"result":{"duration":168641200,"status":"passed"},"line":7,"name":"User enter email 'email' and password 'password'","match":{"arguments":[{"val":"'email'","offset":17},{"val":"'password'","offset":38}],"location":"tek.capstone.bdd.framework.steps.SignInSteps.userEnterEmailAndPassword(java.lang.String,java.lang.String)"},"keyword":"And "},{"result":{"duration":53491600,"status":"passed"},"line":8,"name":"User click on login button","match":{"location":"tek.capstone.bdd.framework.steps.SignInSteps.userClickOnLoginBtn()"},"keyword":"And "},{"result":{"duration":389383300,"status":"passed"},"line":9,"name":"User should be logged in into Account","match":{"location":"tek.capstone.bdd.framework.steps.SignInSteps.userShouldBeLoggedIn()"},"keyword":"And "},{"result":{"duration":72639800,"status":"passed"},"line":10,"name":"User click on Orders section","match":{"location":"tek.capstone.bdd.framework.steps.RetailOrderSteps.userClickOnOrdersSection()"},"keyword":"And "},{"result":{"duration":213203000,"status":"passed"},"line":11,"name":"User click on first order in list","match":{"location":"tek.capstone.bdd.framework.steps.RetailOrderSteps.userClickOnFirstOrderInList()"},"keyword":"And "}]},{"start_timestamp":"2023-03-24T18:01:02.969Z","before":[{"result":{"duration":1795908800,"status":"passed"},"match":{"location":"tek.capstone.bdd.framework.base.BaseUITest.setupTest()"}}],"line":21,"name":"Verify User can Return the order","description":"","id":"retail-order-page;verify-user-can-return-the-order","after":[{"result":{"duration":605873200,"status":"passed"},"match":{"location":"tek.capstone.bdd.framework.base.BaseUITest.closeTest(io.cucumber.java.Scenario)"}}],"type":"scenario","keyword":"Scenario","steps":[{"result":{"duration":169384600,"status":"passed"},"line":22,"name":"User click on Return Items button","match":{"location":"tek.capstone.bdd.framework.steps.RetailOrderSteps.userClickOnReturnItemsButton()"},"keyword":"And "},{"result":{"duration":51393000,"status":"passed"},"line":23,"name":"User select the Return Reason 'Item damaged'","match":{"arguments":[{"val":"'Item damaged'","offset":30}],"location":"tek.capstone.bdd.framework.steps.RetailOrderSteps.userSelectReturnReason(java.lang.String)"},"keyword":"And "},{"result":{"duration":51355500,"status":"passed"},"line":24,"name":"User select the drop off service 'FedEx'","match":{"arguments":[{"val":"'FedEx'","offset":33}],"location":"tek.capstone.bdd.framework.steps.RetailOrderSteps.userSelectDropOffService(java.lang.String)"},"keyword":"And "},{"result":{"duration":50857000,"status":"passed"},"line":25,"name":"User click on Return Order button","match":{"location":"tek.capstone.bdd.framework.steps.RetailOrderSteps.userClickOnReturnOrderBtn()"},"keyword":"And "},{"result":{"duration":157791900,"status":"passed"},"line":26,"name":"a cancelation message should be displayed 'Return was successfull'","match":{"arguments":[{"val":"'Return was successfull'","offset":42}],"location":"tek.capstone.bdd.framework.steps.RetailOrderSteps.cancellationMessageShouldBeDisplayed(java.lang.String)"},"keyword":"Then "}],"tags":[{"name":"@jenkins"},{"name":"@order2"},{"name":"@smoke"}]}],"name":"Retail Order Page","description":"","id":"retail-order-page","keyword":"Feature","uri":"classpath:features/RetailOrder.feature","tags":[{"name":"@jenkins","type":"Tag","location":{"line":1,"column":1}}]},{"line":2,"elements":[{"line":4,"name":"","description":"","type":"background","keyword":"Background","steps":[{"result":{"duration":54433300,"status":"passed"},"line":5,"name":"User is on retail website","match":{"location":"tek.capstone.bdd.framework.steps.SignInSteps.userIsOnRetailWebsite()"},"keyword":"Given "},{"result":{"duration":96668300,"status":"passed"},"line":6,"name":"User click on Sign in option","match":{"location":"tek.capstone.bdd.framework.steps.SignInSteps.userClickOnSignIn()"},"keyword":"When "}]},{"start_timestamp":"2023-03-24T18:01:06.896Z","before":[{"result":{"duration":1787951700,"status":"passed"},"match":{"location":"tek.capstone.bdd.framework.base.BaseUITest.setupTest()"}}],"line":15,"name":"Verify user can create an account into Retail Website","description":"","id":"sign-in-feature;verify-user-can-create-an-account-into-retail-website","after":[{"result":{"duration":592721000,"status":"passed"},"match":{"location":"tek.capstone.bdd.framework.base.BaseUITest.closeTest(io.cucumber.java.Scenario)"}}],"type":"scenario","keyword":"Scenario","steps":[{"result":{"duration":74835400,"status":"passed"},"line":16,"name":"User click on Create New Account button","match":{"location":"tek.capstone.bdd.framework.steps.SignInSteps.userClickOnNewAccountBtn()"},"keyword":"And "},{"result":{"duration":308229800,"status":"passed"},"line":17,"name":"User fill the signUp information with below data","match":{"location":"tek.capstone.bdd.framework.steps.SignInSteps.userFillTheSignUpForm(io.cucumber.datatable.DataTable)"},"rows":[{"cells":["name","email","password","confirmPassword"]},{"cells":["fullName","email","Tek@12345","Tek@12345"]}],"keyword":"And "},{"result":{"duration":51396500,"status":"passed"},"line":20,"name":"User click on SignUp button","match":{"location":"tek.capstone.bdd.framework.steps.SignInSteps.userClickOnSignUpBtn()"},"keyword":"And "},{"result":{"duration":268163700,"status":"passed"},"line":21,"name":"User should be logged into account page","match":{"location":"tek.capstone.bdd.framework.steps.SignInSteps.userShouldBeLoggedIntoAccount()"},"keyword":"Then "}],"tags":[{"name":"@jenkins"},{"name":"@signIn"},{"name":"@smoke"}]}],"name":"Sign In Feature","description":"","id":"sign-in-feature","keyword":"Feature","uri":"classpath:features/SignIn.feature","tags":[{"name":"@jenkins","type":"Tag","location":{"line":1,"column":1}}]}]